krmining/__init__.py
krmining/association_rules/__init__.py
krmining/association_rules/_apriori.py
krmining/association_rules/_evaluate.py
krmining/association_rules/_fpgrowth.py
krmining/association_rules/_tree.py
krmining/classification/__init__.py
krmining/classification/_knn.py
krmining/classification/_logistic_regression.py
krmining/clustering/__init__.py
krmining/clustering/_kmeans.py
krmining/datasets/__init__.py
krmining/datasets/_covid_id.py
krmining/datasets/_dummy_data.py
krmining/external/__init__.py
krmining/external/_wrapper.py
krmining/regression/__init__.py
krmining/regression/_linear_regression.py
krmining/utils/__init__.py
krmining/utils/activation_funtions.py
krmining/utils/association_rules_eval.py
krmining/utils/association_rules_gen.py
krmining/utils/create_tree.py
krmining/utils/least_square.py
krmining/utils/metrics.py
krmining/utils/optimizer.py
krmining/utils/tree.py
keyar_mining-0.0.3.dist-info/LICENSE
keyar_mining-0.0.3.dist-info/METADATA
keyar_mining-0.0.3.dist-info/WHEEL
keyar_mining-0.0.3.dist-info/top_level.txt
keyar_mining-0.0.3.dist-info/RECORD
