Metadata-Version: 2.1
Name: keyar-mining
Version: 0.0.3
Summary: Package for machine learning algorithm and data mining
Home-page: https://github.com/SynitCool/keyar-mining
Author: BASIS / SynitIsCool
Author-email: zolarpixel3@gmail.com
License: MIT
Download-URL: https://github.com/SynitCool/keyar-mining/archive/refs/tags/v0.0.2.tar.gz
Keywords: Data Mining,Machine Learning
Platform: any
Classifier: Development Status :: 5 - Production/Stable
Classifier: License :: OSI Approved :: MIT License
Classifier: Programming Language :: Python :: 3.5
Classifier: Programming Language :: Python :: 3.6
Classifier: Programming Language :: Python :: 3.7
Classifier: Programming Language :: Python :: 3.8
Requires-Python: >= 3.5
License-File: LICENSE
Requires-Dist: numpy
Requires-Dist: pandas
Requires-Dist: setuptools
Requires-Dist: dill
Provides-Extra: docs
Requires-Dist: mkdocs ; extra == 'docs'
